README.md
setup.py
plmap3/__init__.py
plmap3/plmapt.py
plmap3/progress_bar.py
plmap3.egg-info/PKG-INFO
plmap3.egg-info/SOURCES.txt
plmap3.egg-info/dependency_links.txt
plmap3.egg-info/top_level.txt