Metadata-Version: 1.0
Name: plmap3
Version: 1.0.1
Summary: Parallel map using multi-threading for python3
Home-page: https://github.com/CodingVanGogh/parallelization3
Author: Coding Van Gogh
Author-email: UNKNOWN
License: MIT
Keywords: parallelization plmap  plmapt  multi-threading  parallel map python3
Platform: UNKNOWN
